nigerian_only/__init__.py
nigerian_only/apps.py
nigerian_only/decorator.py
nigerian_only/enums.py
nigerian_only/exceptions.py
nigerian_only/middleware.py
nigerian_only/tests.py
nigerian_only/urls.py
nigerian_only/utils.py
nigerian_only/views.py
nigerian_only/migrations/__init__.py
django_nigerians_only-1.0.3.dist-info/LICENSE
django_nigerians_only-1.0.3.dist-info/METADATA
django_nigerians_only-1.0.3.dist-info/WHEEL
django_nigerians_only-1.0.3.dist-info/top_level.txt
django_nigerians_only-1.0.3.dist-info/RECORD
