Metadata-Version: 2.1
Name: django-nigerians-only
Version: 1.0.3
Summary: Django Nigerians Only is a third application that allows developers to restrict access to their applications to only Nigerian users.
Home-page: https://github.com/Afeez1131/nigerians-only
Author: attr: nigerian_only.__author__
Author-email: lawalafeez052@gmail.com
License: MIT
Project-URL: Documentation, https://github.com/Afeez1131/nigerians-only
Project-URL: Source Code, https://github.com/Afeez1131/nigerians-only
Classifier: Operating System :: OS Independent
Classifier: Development Status :: 5 - Production/Stable
Classifier: Framework :: Django
Classifier: Framework :: Django :: 4.1
Classifier: Framework :: Django :: 4.2
Classifier: Programming Language :: Python
Classifier: Programming Language :: Python :: 3
Classifier: Programming Language :: Python :: 3.8
Classifier: Programming Language :: Python :: 3.9
Classifier: Programming Language :: Python :: 3.10
Classifier: License :: OSI Approved :: MIT License
Requires-Python: >=3.9
License-File: LICENSE
Requires-Dist: Django>=4.1
Requires-Dist: geoip2>=4.8.0
